isoforest_eval/__init__.py
isoforest_eval/evaluation.py
isoforest_eval/isolation_runner.py
isoforest_eval/preprocessing.py
isoforest_eval-0.1.0.dist-info/licenses/LICENSE.txt
isoforest_eval-0.1.0.dist-info/METADATA
isoforest_eval-0.1.0.dist-info/WHEEL
isoforest_eval-0.1.0.dist-info/top_level.txt
isoforest_eval-0.1.0.dist-info/RECORD
