Metadata-Version: 2.4
Name: isoforest_eval
Version: 0.1.0
Summary: A library for evaluating Isolation Forest with linear and logistic regression metrics
Author: Your Name
Requires-Python: >=3.7
License-File: LICENSE.txt
Requires-Dist: numpy
Requires-Dist: pandas
Requires-Dist: scikit-learn
Requires-Dist: scipy
Dynamic: author
Dynamic: license-file
Dynamic: requires-dist
Dynamic: requires-python
Dynamic: summary
